{
  "personalInfo": {
    "name": "Valentino Terreno",
    "title": "Desarrollador FullStack",
    "email": "vterreno@gmail.com",
    "githubNickname": "vterreno",
    "location": "C贸rdoba, Argentina ",
    "githubLink": "https://github.com/vterreno",
    "linkedInLink": "https://www.linkedin.com/in/valentino-terreno/",
    "avatar": "https://github.com/vterreno.png",
    "bio": [
      " ",
      " //* [Acerca de m铆]",
      " // Bienvenido a mi porfolio.",
      " ",
      " // Soy estudiante de Ing. En Sistemas de Informaci贸n en la UTN - FRVM. Adem谩s, me desempe帽o como desarrollador web, combinando mis estudioscon la pr谩ctica en el mundo de la programaci贸n. Mi pasi贸n por latecnolog铆a me impulsa a aprender  constantemente, explorando nuevas herramientas y t茅cnicas para crear nuevas  experiencias digitales.",
      " ",
      " //TODO: Agregar link a mi CV"
    ],
    "experiences": [
      " ",
      " //* [Experiencias]",
      " ",
      " //* [2021 - Presente] Desarrollador Web Freelance",
      " // - Desarrollo de sitios web y aplicaciones web.",
      " // - Implementaci贸n de dise帽os responsivos y accesibles.",
      " // - Mantenimiento y actualizaci贸n de sitios web.",
      " ",
      " //* [2020 - 2021] Desarrollador Web en Globant",
      " // - Desarrollo de aplicaciones web y sitios web.",
      " // - Implementaci贸n de dise帽os responsivos y accesibles.",
      " // - Mantenimiento y actualizaci贸n de sitios web.",
      " ",
      " //* [2019 - 2020] Desarrollador Web en MercadoLibre",
      " // - Desarrollo de aplicaciones web y sitios web.",
      " // - Implementaci贸n de dise帽os responsivos y accesibles.",
      " // - Mantenimiento y actualizaci贸n de sitios web.",
      " "
    ],
    "education": [
      " ",
      " //* [Educaci贸n]", 
      " ",
      "//* [2023 - Presente] DevelHope",
      "// Curso Full Stack Developer",
      "// Tecnolog铆as: HTML, CSS, SCSS, JavaScript, React, TypeScript, Node.js, Tailwind CSS, Git",
      " ",
      "//* [2021 - 2026] Universidad Tecnol贸gica Nacional - FRVM", 
      "// Ingenier铆a en Sistemas de Informaci贸n",
      " ",
      "//* [2010 - 2015] Instituto T茅cnico Comercial",
      "// Diploma en Administraci贸n, Finanzas y Marketing",
      "// Calificaci贸n final: 92/100",
      " ",
      "//* [Formaci贸n continua]",
      "// Participo regularmente en talleres y cursos en l铆nea para mantenerme actualizado sobre las 煤ltimas tecnolog铆as y las mejores pr谩cticas en el desarrollo web.",
      " "
    ],
    "certifications": [
      {
        "title": "Certificaci贸n en Desarrollo Web",
        "organization": "Coursera",
        "link": "https://www.coursera.org/",
        "date": "2021"
      },
      {
        "title": "Certificaci贸n en Ingl茅s",
        "organization": "OpenEnglish",
        "link": "https://www.openenglish.com/",
        "date": "2020"
      } 
    ]
  },
  "skills": [
    {
      "name": "HTML",
      "checked": true
    },
    {
      "name": "SASS",
      "checked": true
    },
    {
      "name": "CSS",
      "checked": true
    },
    {
      "name": "Vue.js",
      "checked": false
    },
    {
      "name": "JavaScript",
      "checked": true
    },
    {
      "name": "Tailwind",
      "checked": true
    },
    {
      "name": "React",
      "checked": true
    },
    {
      "name": "Bootstrap",
      "checked": false
    },
    {
      "name": "TypeScript",
      "checked": true
    },
    {
      "name": "Git",
      "checked": true
    },
    {
      "name": "Node",
      "checked": true
    }
  ],
  "projects": [
    {
      "title": "miMascotapp",
      "githubLink": "#",
      "demoLink": "https://mimascotapp.com.ar/",
      "content": [
        " ",
        " //* [Proyecto]: _miMascotapp",
        " ",
        " // Landing page de una aplicaci贸n mobile para la gesti贸n integral del cuidado de mascotas. El proyecto fue desarrollado en equipo y se utiliz贸 la metodolog铆a Agile para la organizaci贸n del trabajo. El dise帽o fue realizado en Figma y se complet贸 en 3 sprints. Adem谩s, la web es responsive y accesible.",
        " "
      ],
      "images": [
        {
          "src": "/mimascotapp.webp",
          "alt": "miMascotapp"
        }
      ],
      "technologies": [
        "HTML",
        "CSS",
        "Agile",
        "Trello"
      ]
    },
    {
      "title": "devPorfolio",
      "githubLink": "#",
      "demoLink": "#",
      "content": [
        " ",
        " //* [Proyecto]: _devPorfolio",
        " ",
        " // Porfolio personal para mostrar mis habilidades y proyectos. El proyecto fue desarrollado en solitario y se utiliz贸 la metodolog铆a Agile para la organizaci贸n del trabajo. El dise帽o fue realizado en Figma y se complet贸 en 2 sprints. Adem谩s, la web es responsive y accesible.",
        " "
      ],
      "images": [
        {
          "title": "Hero",
          "src": "/devporfolio_1.webp",
          "alt": "devPorfolio - Hero"
        },
        {
          "title": "Acerca de mi",
          "src": "/devporfolio_2.webp",
          "alt": "devPorfolio - Acerca de mi"
        }
      ],
      "technologies": [
        "HTML",
        "CSS",
        "Agile",
        "Trello"
      ]
    }
  ],
  "codeSnippets": {
    "apiExample": {
      "title": "Ejemplo API",
      "description": "Llamada a una API mediante generateTemplateHTML + renderizaci贸n en HTML de los datos obtenidos de una funci贸n as铆ncrona"
    }
  }
}